BelarusianConverter/__init__.py
BelarusianConverter/arabic.py
BelarusianConverter/belarusianconverter.py
BelarusianConverter/latin1929.py
BelarusianConverter/latin1962.py
BelarusianConverter/latinMP.py
BelarusianConverter/latinUN.py
BelarusianConverter/romanization2023.py
belarusianconverter-0.0.6.dist-info/LICENSE
belarusianconverter-0.0.6.dist-info/METADATA
belarusianconverter-0.0.6.dist-info/WHEEL
belarusianconverter-0.0.6.dist-info/top_level.txt
belarusianconverter-0.0.6.dist-info/RECORD
