Metadata-Version: 2.1
Name: belarusianconverter
Version: 0.0.6
Summary: Library for convertation Belarusian texts from Cyrillic to other Belarusian alphabets
Home-page: https://github.com/alelisicyna/BelarusianConverter
Author: alelisicyna
Author-email: alelisicyna@gmail.com
Project-URL: GitHub, https://github.com/alelisicyna
Keywords: files speedfiles spellings spelling Belarusian Belarus convert converter alphabets
Classifier: License :: OSI Approved :: GNU Affero General Public License v3 or later (AGPLv3+)
Requires-Python: >=3.6
License-File: LICENSE
